pghaicker/__init__.py
pghaicker/cli.py
pghaicker-0.1.2.dist-info/METADATA
pghaicker-0.1.2.dist-info/WHEEL
pghaicker-0.1.2.dist-info/entry_points.txt
pghaicker-0.1.2.dist-info/top_level.txt
pghaicker-0.1.2.dist-info/RECORD
