Metadata-Version: 2.4
Name: pghaicker
Version: 0.1.2
Summary: AI Assistant for Postgres Hackers
Author-email: Florents Tselai <florents.tselai@gmail.com>
License-Expression: MIT
Requires-Python: >=3.8
Requires-Dist: google-genai
Requires-Dist: pypandoc
Requires-Dist: click
Provides-Extra: dev
Requires-Dist: pytest; extra == "dev"
Requires-Dist: black; extra == "dev"
